[
    {"plaatsId": "23","branches": ["101-agf"] },
    {"plaatsId": "24","branches": ["101-agf"] },
    {"plaatsId": "5","branches": ["103-brood-banket"] },
    {"plaatsId": "6","branches": ["103-brood-banket"] },
    {"plaatsId": "8","branches": ["107-vis-nat"] },
    {"plaatsId": "9","branches": ["107-vis-nat"] },
    {"plaatsId": "7","branches": ["108-vleeswaren"] },
    {"plaatsId": "1","branches": ["201-broodjes-belegd"] },
    {"plaatsId": "17","branches": ["101-agf"] },
    {"plaatsId": "18","branches": ["101-agf"] },
    {"plaatsId": "19","branches": ["102-bio-health-fairtrade"] },
    {"plaatsId": "25","branches": ["102-bio-health-fairtrade"] },
    {"plaatsId": "10","branches": ["104-hummus-kruiden-olijven"] },
    {"plaatsId": "22","branches": ["104-hummus-kruiden-olijven"] },
    {"plaatsId": "20","branches": ["105-noten-zuidvruchten"] },
    {"plaatsId": "21","branches": ["105-noten-zuidvruchten"] },
    {"plaatsId": "26","branches": ["110-poelier"] },
    {"plaatsId": "11","branches": ["109-zuivel-eieren"] },
    {"plaatsId": "12","branches": ["109-zuivel-eieren"] },
    {"plaatsId": "13","branches": ["109-zuivel-eieren"] },
    {"plaatsId": "14","branches": ["302-bloemen-planten"] },
    {"plaatsId": "15","branches": ["302-bloemen-planten"] },
    {"plaatsId": "16","branches": ["302-bloemen-planten"] },
    {"plaatsId": "2"  },
    {"plaatsId": "3"  },
    {"plaatsId": "4"  }
]