[
    { "plaatsId": "101", "branches": ["bak", "107-vis-nat"], "verkoopinrichting": ["eigen-materieel"] },
    { "plaatsId": "103", "branches": ["bak", "107-vis-nat"], "verkoopinrichting": ["eigen-materieel"] },
    { "plaatsId": "105", "branches": ["bak", "107-vis-nat"], "verkoopinrichting": ["eigen-materieel"], "properties": ["boom"] },
    { "plaatsId": "107", "branches": ["bak", "107-vis-nat"], "verkoopinrichting": ["eigen-materieel"] },
    { "plaatsId": "109", "branches": ["bak", "107-vis-nat"], "verkoopinrichting": ["eigen-materieel"] },
    { "plaatsId": "111", "branches": ["104-hummus-kruiden-olijven"], "properties": ["electra", "boom"] },
    { "plaatsId": "113", "branches": ["104-hummus-kruiden-olijven"] },
    { "plaatsId": "115", "branches": ["bak", "105-noten-zuidvruchten"], "verkoopinrichting": ["eigen-materieel"] },
    { "plaatsId": "117", "branches": ["bak", "105-noten-zuidvruchten"], "verkoopinrichting": ["eigen-materieel"] },
    { "plaatsId": "119", "branches": ["bak", "105-noten-zuidvruchten"], "verkoopinrichting": ["eigen-materieel"], "properties": ["boom"] },
    { "plaatsId": "121", "branches": ["309-kleding-volwassenen-hoofddeksels"] },
    { "plaatsId": "123", "branches": ["309-kleding-volwassenen-hoofddeksels"] },
    { "plaatsId": "125", "branches": ["309-kleding-volwassenen-hoofddeksels"] },
    { "plaatsId": "127", "branches": ["302-bloemen-planten"] },
    { "plaatsId": "129", "branches": ["302-bloemen-planten"], "properties": ["electra", "boom"] },
    { "plaatsId": "131", "branches": ["109-zuivel-eieren"] },
    { "plaatsId": "133", "branches": ["109-zuivel-eieren"] },
    { "plaatsId": "135", "branches": ["bak", "206-oudhollands-gebak"] },
    { "plaatsId": "137", "branches": ["bak", "206-oudhollands-gebak"], "properties": ["boom"] },
    { "plaatsId": "139", "branches": ["302-bloemen-planten"] },
    { "plaatsId": "141", "branches": ["302-bloemen-planten"] },
    { "plaatsId": "143", "branches": ["101-agf"] },
    { "plaatsId": "145", "branches": ["101-agf"], "properties": ["boom"] },
    { "plaatsId": "147", "branches": ["bak", "201-broodjes-belegd"], "verkoopinrichting": ["eigen-materieel"] },
    { "plaatsId": "149", "branches": ["bak", "110-poelier"], "verkoopinrichting": ["eigen-materieel"], "properties": ["electra"] },
    { "plaatsId": "151", "branches": ["bak", "110-poelier"], "verkoopinrichting": ["eigen-materieel"] },
    { "plaatsId": "153", "branches": ["305-horloges-brillen-sieraden"] },
    { "plaatsId": "155", "branches": ["315-schoenen-tassen-lederwaren"] },
    { "plaatsId": "157", "branches": ["315-schoenen-tassen-lederwaren"] },
    { "plaatsId": "159", "branches": ["309-kleding-volwassenen-hoofddeksels"] },
    { "plaatsId": "161", "branches": ["309-kleding-volwassenen-hoofddeksels"] },

    { "plaatsId": "201", "branches": ["bak", "103-brood-banket"], "verkoopinrichting": ["eigen-materieel"] },
    { "plaatsId": "203", "branches": ["bak", "103-brood-banket"], "verkoopinrichting": ["eigen-materieel"] },
    { "plaatsId": "205", "branches": ["315-schoenen-tassen-lederwaren"], "properties": ["boom"] },
    { "plaatsId": "207", "branches": ["315-schoenen-tassen-lederwaren"] },
    { "plaatsId": "209", "branches": ["308-kleding-onder-beenmode-sokken"], "properties": ["electra"] },
    { "plaatsId": "211", "branches": ["308-kleding-onder-beenmode-sokken"] },
    { "plaatsId": "213", "branches": ["101-agf"], "properties": ["boom"] },
    { "plaatsId": "215", "branches": ["101-agf"] },
    { "plaatsId": "217", "branches": ["101-agf"] },
    { "plaatsId": "219", "branches": ["101-agf"] },
    { "plaatsId": "221", "branches": ["101-agf"], "properties": ["boom"] },
    { "plaatsId": "223", "branches": ["101-agf"] },
    { "plaatsId": "225", "branches": ["109-zuivel-eieren"], "properties": ["electra"] },
    { "plaatsId": "227", "branches": ["109-zuivel-eieren"], "properties": ["boom"] },
    { "plaatsId": "229", "branches": ["109-zuivel-eieren"] },
    { "plaatsId": "231", "branches": ["303-boeken-stripboeken-muziek-film"] },
    { "plaatsId": "233", "branches": ["303-boeken-stripboeken-muziek-film"] },
    { "plaatsId": "235", "branches": ["bak", "108-vleeswaren"], "verkoopinrichting": ["eigen-materieel"] },
    { "plaatsId": "237", "branches": ["bak", "108-vleeswaren"], "verkoopinrichting": ["eigen-materieel"] },
    { "plaatsId": "239", "branches": ["302-bloemen-planten"], "properties": ["electra", "boom"] },
    { "plaatsId": "241", "branches": ["302-bloemen-planten"] },
    { "plaatsId": "243", "branches": ["bak", "205-loempias"], "verkoopinrichting": ["eigen-materieel"] },
    { "plaatsId": "245", "branches": ["bak", "205-loempias"], "verkoopinrichting": ["eigen-materieel"] },

    { "plaatsId": "301", "branches": ["101-agf"] },
    { "plaatsId": "303", "branches": ["101-agf"] },
    { "plaatsId": "305", "branches": ["101-agf"], "properties": ["boom"] },
    { "plaatsId": "307", "branches": ["109-zuivel-eieren"] },
    { "plaatsId": "309", "branches": ["309-kleding-volwassenen-hoofddeksels"], "properties": ["boom"] },
    { "plaatsId": "311", "branches": ["309-kleding-volwassenen-hoofddeksels"], "properties": ["electra"] },
    { "plaatsId": "313", "branches": ["302-bloemen-planten"], "properties": ["boom"] },
    { "plaatsId": "315", "branches": ["302-bloemen-planten"] },
    { "plaatsId": "317", "branches": ["309-kleding-volwassenen-hoofddeksels"], "properties": ["boom"] },
    { "plaatsId": "319", "branches": ["309-kleding-volwassenen-hoofddeksels"] },
    { "plaatsId": "321", "branches": ["306-huishoudelijke-artikelen-meubels-apparatuur"], "properties": ["boom"] },
    { "plaatsId": "323", "branches": ["306-huishoudelijke-artikelen-meubels-apparatuur"] },
    { "plaatsId": "325", "branches": ["104-hummus-kruiden-olijven"], "verkoopinrichting": ["eigen-materieel"] },
    { "plaatsId": "327", "branches": ["104-hummus-kruiden-olijven"], "verkoopinrichting": ["eigen-materieel"], "properties": ["electra"] },
    { "plaatsId": "329", "branches": ["309-kleding-volwassenen-hoofddeksels"], "properties": ["boom"] },
    { "plaatsId": "331", "branches": ["309-kleding-volwassenen-hoofddeksels"] },
    { "plaatsId": "333", "branches": ["309-kleding-volwassenen-hoofddeksels"] },
    { "plaatsId": "335", "branches": ["309-kleding-volwassenen-hoofddeksels"] },
    { "plaatsId": "337", "branches": ["101-agf"], "properties": ["boom"] },
    { "plaatsId": "339", "branches": ["bak", "201-broodjes-belegd"] },
    { "plaatsId": "341", "branches": ["bak", "201-broodjes-belegd"] }, 
    { "plaatsId": "343", "branches": ["305-horloges-brillen-sieraden"], "properties": ["electra", "boom"] },
    { "plaatsId": "345", "branches": ["305-horloges-brillen-sieraden"] },
    { "plaatsId": "347", "branches": ["309-kleding-volwassenen-hoofddeksels"] },
    { "plaatsId": "349", "branches": ["309-kleding-volwassenen-hoofddeksels"] },
    { "plaatsId": "351", "branches": ["302-bloemen-planten"] }, 
    { "plaatsId": "353", "branches": ["302-bloemen-planten"] },

    { "plaatsId": "401", "branches": ["316-souvenirs"] },
    { "plaatsId": "403", "branches": ["316-souvenirs"] },
    { "plaatsId": "405", "branches": ["305-horloges-brillen-sieraden"], "properties": ["boom"] },
    { "plaatsId": "407", "branches": ["313-parfumerie-drogisterij-persoonlijke-verzorging"] },
    { "plaatsId": "409", "branches": ["313-parfumerie-drogisterij-persoonlijke-verzorging"], "properties": ["electra"] },
    { "plaatsId": "411", "branches": ["305-horloges-brillen-sieraden"] },
    { "plaatsId": "413", "branches": ["315-schoenen-tassen-lederwaren"], "properties": ["boom"] },
    { "plaatsId": "415", "branches": ["315-schoenen-tassen-lederwaren"] },
    { "plaatsId": "417", "branches": ["309-kleding-volwassenen-hoofddeksels"] },
    { "plaatsId": "419", "branches": ["309-kleding-volwassenen-hoofddeksels"] },
    { "plaatsId": "421", "branches": ["315-schoenen-tassen-lederwaren"], "properties": ["boom"] },
    { "plaatsId": "423", "branches": ["315-schoenen-tassen-lederwaren"] },
    { "plaatsId": "425", "branches": ["316-souvenirs"] },
    { "plaatsId": "427", "branches": ["316-souvenirs"] },
    { "plaatsId": "429", "branches": ["302-bloemen-planten"], "properties": ["boom"] },
    { "plaatsId": "431", "branches": ["302-bloemen-planten"], "properties": ["electra"] },
    { "plaatsId": "433", "branches": ["315-schoenen-tassen-lederwaren"] },
    { "plaatsId": "435", "branches": ["315-schoenen-tassen-lederwaren"], "properties": ["boom"] },
    { "plaatsId": "435a", "branches": ["bak", "107-vis-nat"], "verkoopinrichting": ["eigen-materieel"] },
    { "plaatsId": "437", "branches": ["bak", "107-vis-nat"], "verkoopinrichting": ["eigen-materieel"] },
    { "plaatsId": "439", "branches": ["bak", "107-vis-nat"], "verkoopinrichting": ["eigen-materieel"] },
    { "plaatsId": "441", "properties": ["boom"] },
    { "plaatsId": "443", "branches": ["313-parfumerie-drogisterij-persoonlijke-verzorging"] },
    { "plaatsId": "445", "branches": ["304-dierenbijnodigdheden"] },
    { "plaatsId": "447", "branches": ["304-dierenbijnodigdheden"] },
    { "plaatsId": "449" },
    { "plaatsId": "451", "properties": ["boom"] },
    { "plaatsId": "453", "branches": ["320-fietsen-auto-accessoires"] },
    { "plaatsId": "455", "branches": ["320-fietsen-auto-accessoires"] }
]