[
    { "plaatsId": "2", "branches": ["101-agf"] },
    { "plaatsId": "3", "branches": ["101-agf"] },
    { "plaatsId": "4", "branches": ["101-agf"] },
    { "plaatsId": "5", "branches": ["bak", "103-brood-banket"], "verkoopinrichting": ["eigen-materieel"] },
    { "plaatsId": "6", "branches": ["bak", "103-brood-banket"], "verkoopinrichting": ["eigen-materieel"] },
    { "plaatsId": "7", "branches": ["bak", "103-brood-banket"] },
    { "plaatsId": "8", "branches": ["bak", "102-bio-health-fairtrade"], "verkoopinrichting": ["eigen-materieel"] },
    { "plaatsId": "9", "branches": ["bak", "102-bio-health-fairtrade"], "verkoopinrichting": ["eigen-materieel"] },
    { "plaatsId": "10", "branches": ["bak", "103-brood-banket"], "verkoopinrichting": ["eigen-materieel"] },
    { "plaatsId": "11" },
    { "plaatsId": "12", "branches": ["101-agf"] },
    { "plaatsId": "13", "branches": ["101-agf"] },
    { "plaatsId": "14", "branches": ["101-agf"] },
    { "plaatsId": "15", "branches": ["109-zuivel-eieren"] },
    { "plaatsId": "16", "branches": ["209-vis-gebakken"] },   
    { "plaatsId": "17", "branches": ["109-zuivel-eieren"] },
    { "plaatsId": "18", "branches": ["109-zuivel-eieren"] },
    { "plaatsId": "19", "branches": ["102-bio-health-fairtrade"] },
    { "plaatsId": "20", "branches": ["107-vis-nat"] },
    { "plaatsId": "21", "branches": ["104-hummus-kruiden-olijven"] },
    { "plaatsId": "22", "branches": ["104-hummus-kruiden-olijven"] },
    { "plaatsId": "23", "branches": ["101-agf"] },
    { "plaatsId": "24", "branches": ["101-agf"] },
    { "plaatsId": "25", "branches": ["313-parfumerie-drogisterij-persoonlijke-verzorging"] },
    { "plaatsId": "26", "branches": ["104-hummus-kruiden-olijven"] },
    { "plaatsId": "27", "branches": ["104-hummus-kruiden-olijven"] },
    { "plaatsId": "28", "branches": ["bak", "207-grill-frituur"], "verkoopinrichting": ["eigen-materieel"] },
    { "plaatsId": "30", "branches": ["109-zuivel-eieren"], "verkoopinrichting": ["eigen-materieel"] },
    { "plaatsId": "31", "branches": ["109-zuivel-eieren"], "verkoopinrichting": ["eigen-materieel"] },
    { "plaatsId": "32", "branches": ["108-vleeswaren"], "verkoopinrichting": ["eigen-materieel"] },
    { "plaatsId": "33", "branches": ["108-vleeswaren"], "verkoopinrichting": ["eigen-materieel"] },
    { "plaatsId": "34", "branches": ["102-bio-health-fairtrade"] },
    { "plaatsId": "35", "branches": ["102-bio-health-fairtrade"] },
    { "plaatsId": "36", "branches": ["bak", "207-grill-frituur"] },
    { "plaatsId": "37", "branches": ["bak", "206-oudhollands-gebak"] },
    { "plaatsId": "38", "branches": ["bak", "206-oudhollands-gebak"], "verkoopinrichting": ["eigen-materieel"] }
]
